wagtail_lms/__init__.py
wagtail_lms/admin.py
wagtail_lms/apps.py
wagtail_lms/conf.py
wagtail_lms/migrations/0001_initial.py
wagtail_lms/migrations/__init__.py
wagtail_lms/models.py
wagtail_lms/static/wagtail_lms/css/course.css
wagtail_lms/static/wagtail_lms/css/scorm-admin.css
wagtail_lms/static/wagtail_lms/js/scorm-admin.js
wagtail_lms/templates/wagtail_lms/course_page.html
wagtail_lms/templates/wagtail_lms/scorm_package_list.html
wagtail_lms/templates/wagtail_lms/scorm_player.html
wagtail_lms/urls.py
wagtail_lms/views.py
wagtail_lms/wagtail_hooks.py
wagtail_lms-0.4.1.dist-info/WHEEL
wagtail_lms-0.4.1.dist-info/METADATA
wagtail_lms-0.4.1.dist-info/RECORD
