Metadata-Version: 2.3
Name: wagtail_lms
Version: 0.4.1
Summary: A Learning Management System extension for Wagtail with SCORM 1.2/2004 support
Keywords: wagtail,django,lms,scorm,xAPI,e-learning,education
Author: Felipe Villegas
Author-email: Felipe Villegas <felavid@gmail.com>
License: MIT
Classifier: Development Status :: 3 - Alpha
Classifier: Environment :: Web Environment
Classifier: Framework :: Django
Classifier: Framework :: Django :: 4.2
Classifier: Framework :: Django :: 5.0
Classifier: Framework :: Django :: 5.1
Classifier: Framework :: Django :: 5.2
Classifier: Framework :: Wagtail
Classifier: Framework :: Wagtail :: 6
Classifier: Framework :: Wagtail :: 7
Classifier: Intended Audience :: Developers
Classifier: License :: OSI Approved :: MIT License
Classifier: Operating System :: OS Independent
Classifier: Programming Language :: Python
Classifier: Programming Language :: Python :: 3
Classifier: Programming Language :: Python :: 3.11
Classifier: Programming Language :: Python :: 3.12
Classifier: Programming Language :: Python :: 3.13
Classifier: Topic :: Education
Classifier: Topic :: Internet :: WWW/HTTP
Classifier: Topic :: Internet :: WWW/HTTP :: Dynamic Content
Requires-Dist: django>=4.2
Requires-Dist: wagtail>=6.0
Requires-Dist: pytest>=7.4.2 ; extra == 'testing'
Requires-Dist: pytest-django>=4.5.2 ; extra == 'testing'
Requires-Dist: pytest-cov>=4.0 ; extra == 'testing'
Requires-Python: >=3.11
Project-URL: Bug Tracker, https://github.com/dr-rompecabezas/wagtail-lms/issues
Project-URL: Changelog, https://github.com/dr-rompecabezas/wagtail-lms/blob/main/CHANGELOG.md
Project-URL: Documentation, https://wagtail-lms.readthedocs.io
Project-URL: Homepage, https://github.com/dr-rompecabezas/wagtail-lms
Project-URL: Repository, https://github.com/dr-rompecabezas/wagtail-lms
Provides-Extra: testing
